LICENSE
LICENSE.txt
README.rst
setup.cfg
setup.py
smarthomeThailand/__init__.py
smarthomeThailand/smarthome.py
smarthomeThailand.egg-info/PKG-INFO
smarthomeThailand.egg-info/SOURCES.txt
smarthomeThailand.egg-info/dependency_links.txt
smarthomeThailand.egg-info/top_level.txt